ld_plot/__init__.py
ld_plot/ld_plot.py
ld_plot-0.0.2.1.dist-info/LICENSE
ld_plot-0.0.2.1.dist-info/METADATA
ld_plot-0.0.2.1.dist-info/WHEEL
ld_plot-0.0.2.1.dist-info/top_level.txt
ld_plot-0.0.2.1.dist-info/RECORD
