Metadata-Version: 2.1
Name: ld-plot
Version: 0.0.2.1
Summary: Plot Linkage Disequilibrium
Home-page: https://github.com/NikKonst/ld_plot
Author: Nikita Konstantinovskiy
Author-email: nikkonst@icloud.com
License: UNKNOWN
Project-URL: Bug Tracker, https://github.com/NikKonst/ld_plot/issues
Platform: UNKNOWN
Classifier: Programming Language :: Python :: 3
Classifier: License :: OSI Approved :: MIT License
Classifier: Operating System :: OS Independent
Requires-Python: >=3.6
License-File: LICENSE
